naver_dict_api/__init__.py
naver_dict_api/client.py
naver_dict_api-0.1.1.dist-info/licenses/LICENSE
naver_dict_api-0.1.1.dist-info/WHEEL
naver_dict_api-0.1.1.dist-info/METADATA
naver_dict_api-0.1.1.dist-info/RECORD
