Metadata-Version: 2.4
Name: naver-dict-api
Version: 0.1.1
Summary: A Python library for accessing Naver Dictionary API
Keywords: naver,dictionary,hanja,korean,api,translator
Author: roamer3147
Author-email: roamer3147 <noreply@example.com>
License-Expression: MIT
License-File: LICENSE
Classifier: Development Status :: 4 - Beta
Classifier: Intended Audience :: Developers
Classifier: License :: OSI Approved :: MIT License
Classifier: Programming Language :: Python :: 3
Classifier: Programming Language :: Python :: 3.13
Classifier: Operating System :: OS Independent
Classifier: Topic :: Software Development :: Libraries :: Python Modules
Classifier: Topic :: Text Processing :: Linguistic
Requires-Dist: curl-cffi>=0.13.0
Requires-Dist: pytest>=8.0.0 ; extra == 'dev'
Requires-Dist: pytest-cov>=4.1.0 ; extra == 'dev'
Requires-Python: >=3.13
Project-URL: Documentation, https://github.com/gembleman/naver-dict-api#readme
Project-URL: Homepage, https://github.com/gembleman/naver-dict-api
Project-URL: Issues, https://github.com/gembleman/naver-dict-api/issues
Project-URL: Repository, https://github.com/gembleman/naver-dict-api
Provides-Extra: dev
